{
  "version": "1.0.0",
  "feature": "AI Answer Markdown Formatting and Chat Context Persistence with Rolling Window",
  "freeze_phase": "hot",
  "contracts": {
    "shared": {
      "exports": {
        "public": {
          "types": [
            "MarkdownConfig",
            "RollingWindowConfig"
          ],
          "functions": [
            "applyRollingWindow",
            "sanitizeMarkdown"
          ],
          "constants": [
            "DEFAULT_MARKDOWN_CONFIG",
            "DEFAULT_ROLLING_WINDOW_CONFIG"
          ]
        },
        "internal": [
          "pruneOldestMessages",
          "validateMarkdownContent"
        ]
      },
      "schemas": {
        "MarkdownConfig": {
          "type": "object",
          "properties": {
            "allowedElements": { "type": "array", "items": { "type": "string" } },
            "disallowedElements": { "type": "array", "items": { "type": "string" } },
            "sanitize": { "type": "boolean" }
          },
          "required": ["sanitize"]
        },
        "RollingWindowConfig": {
          "type": "object",
          "properties": {
            "maxMessages": { "type": "number", "minimum": 1 },
            "preserveSystemMessages": { "type": "boolean" }
          },
          "required": ["maxMessages"]
        }
      }
    },
    "frontend": {
      "imports_from_shared": [
        "MarkdownConfig",
        "RollingWindowConfig",
        "applyRollingWindow",
        "DEFAULT_MARKDOWN_CONFIG",
        "DEFAULT_ROLLING_WINDOW_CONFIG"
      ],
      "exports": [
        "MarkdownRenderer"
      ],
      "allowed_internal_helpers": true,
      "file_naming": {
        "pattern": "app/components/{PascalName}/{PascalName}.tsx",
        "example": "app/components/MarkdownRenderer/MarkdownRenderer.tsx"
      }
    }
  },
  "boundaries": {
    "shared_to_frontend": {
      "data_shape": "MarkdownConfig | RollingWindowConfig",
      "serialization": "JSON",
      "error_shape": { "code": "string", "message": "string" }
    }
  },
  "dependency_graph": {
    "shared": {
      "depends_on": [],
      "blocks": ["frontend"]
    },
    "frontend": {
      "depends_on": ["shared"],
      "blocks": []
    }
  },
  "best_practices": {
    "markdown_security": {
      "library": "Use react-markdown with rehype-sanitize plugin for XSS protection",
      "configuration": "Restrict allowed elements to safe HTML tags (p, strong, em, code, pre, ul, ol, li, blockquote, a)",
      "url_filtering": "Block javascript: and data: protocols in URLs via urlTransform",
      "custom_components": "Use custom components for code blocks with syntax highlighting if needed"
    },
    "rolling_window": {
      "implementation": "Apply rolling window logic in useChat hook before saving to localStorage",
      "pruning_strategy": "Remove oldest messages first when maxMessages exceeded",
      "system_messages": "Preserve system messages if preserveSystemMessages is true",
      "performance": "Limit to 20-50 messages to prevent localStorage quota issues"
    },
    "react_patterns": {
      "component_isolation": "MarkdownRenderer should be a reusable, independent component",
      "memoization": "Use React.memo for MarkdownRenderer to prevent unnecessary re-renders",
      "error_boundaries": "Wrap markdown rendering in error boundary to handle parsing errors"
    },
    "css_styling": {
      "custom_css": "Use app/styles/ for all styling (no Tailwind)",
      "markdown_styling": "Create markdown.css module for markdown-specific styles",
      "code_blocks": "Style code blocks with dark theme and proper spacing",
      "responsive": "Ensure markdown content is responsive on mobile devices"
    },
    "storage_best_practices": {
      "error_handling": "Handle QuotaExceededError gracefully with user notification",
      "validation": "Validate stored data structure before loading from localStorage",
      "fallback": "Provide fallback to empty array if localStorage data is corrupted"
    }
  },
  "codebase_impact": {
    "files_to_modify": [
      "lib/hooks/useChat.ts - Add rolling window logic and update ChatMessage type",
      "lib/constants.ts - Add rolling window constants",
      "app/components/StreamingChat/StreamingChat.tsx - Replace plain text with MarkdownRenderer",
      "lib/types/ai.ts - Add markdown-related types if needed",
      "package.json - Add react-markdown, rehype-sanitize dependencies"
    ],
    "files_to_create": [
      "lib/utils/markdown-config.ts - Markdown configuration and utilities",
      "lib/utils/rolling-window.ts - Rolling window logic utilities",
      "app/components/MarkdownRenderer/MarkdownRenderer.tsx - Markdown rendering component",
      "app/components/MarkdownRenderer/MarkdownRenderer.css - Markdown styling",
      "app/styles/markdown.css - Global markdown styles"
    ],
    "css_best_practices": [
      "Use custom CSS classes from app/styles/ (no Tailwind)",
      "Create markdown.css for markdown-specific styles",
      "Style code blocks with proper syntax highlighting colors",
      "Ensure links have proper hover states and external link indicators",
      "Style blockquotes with left border and background color",
      "Style tables with proper borders and responsive behavior"
    ]
  }
}
